jupyterlite_clojure_kernel/__init__.py
jupyterlite_clojure_kernel/_version.py
jupyterlite_clojure_kernel/labextension/package.json
jupyterlite_clojure_kernel/labextension/static/509.34091f59ca56b8dcdd9f.js
jupyterlite_clojure_kernel/labextension/static/722.105f7c3a1d59a1e67f97.js
jupyterlite_clojure_kernel/labextension/static/remoteEntry.ac13256d523f8b53f02d.js
jupyterlite_clojure_kernel/labextension/static/style.js
jupyterlite_clojure_kernel/labextension/static/third-party-licenses.json
jupyterlite_clojure_kernel_canary-0.1.1.data/data/share/jupyter/labextensions/jupyterlite-clojure-kernel/package.json
jupyterlite_clojure_kernel_canary-0.1.1.data/data/share/jupyter/labextensions/jupyterlite-clojure-kernel/static/509.34091f59ca56b8dcdd9f.js
jupyterlite_clojure_kernel_canary-0.1.1.data/data/share/jupyter/labextensions/jupyterlite-clojure-kernel/static/722.105f7c3a1d59a1e67f97.js
jupyterlite_clojure_kernel_canary-0.1.1.data/data/share/jupyter/labextensions/jupyterlite-clojure-kernel/static/remoteEntry.ac13256d523f8b53f02d.js
jupyterlite_clojure_kernel_canary-0.1.1.data/data/share/jupyter/labextensions/jupyterlite-clojure-kernel/static/style.js
jupyterlite_clojure_kernel_canary-0.1.1.data/data/share/jupyter/labextensions/jupyterlite-clojure-kernel/static/third-party-licenses.json
jupyterlite_clojure_kernel_canary-0.1.1.dist-info/METADATA
jupyterlite_clojure_kernel_canary-0.1.1.dist-info/WHEEL
jupyterlite_clojure_kernel_canary-0.1.1.dist-info/entry_points.txt
jupyterlite_clojure_kernel_canary-0.1.1.dist-info/licenses/LICENSE
jupyterlite_clojure_kernel_canary-0.1.1.dist-info/RECORD
