Metadata-Version: 2.3
Name: jupyterlite-clojure-kernel-canary
Version: 0.1.1
Summary: A Clojure Kernel for JupyterLite using `sci`
Project-URL: Source, https://github.com/bencode/jupyterlite-clojure-kernel
Author-email: bencode <bencode@163.com>
License: MIT
Keywords: clojure,jupyter,jupyterlab,jupyterlite
Classifier: Framework :: Jupyter
Classifier: Framework :: Jupyter :: JupyterLab
Classifier: Framework :: Jupyter :: JupyterLab :: 4
Classifier: License :: OSI Approved :: MIT License
Requires-Python: >=3.8
Requires-Dist: jupyterlite-core<0.5.0,>=0.4.0
